flask_dbhydra/__init__.py
flask_dbhydra/flask_dbhydra_core.py
flask_dbhydra-0.1.7.dist-info/LICENSE
flask_dbhydra-0.1.7.dist-info/METADATA
flask_dbhydra-0.1.7.dist-info/WHEEL
flask_dbhydra-0.1.7.dist-info/top_level.txt
flask_dbhydra-0.1.7.dist-info/RECORD
