Metadata-Version: 2.1
Name: flask-dbhydra
Version: 0.1.7
Summary: Autogenerate Flask API for dbhydra ORM DB structure
Home-page: https://github.com/DovaX/flask_dbhydra
Author: DovaX
Author-email: dovax.ai@gmail.com
License: UNKNOWN
Platform: UNKNOWN
Classifier: Programming Language :: Python :: 3
Classifier: License :: OSI Approved :: MIT License
Classifier: Operating System :: OS Independent
Requires-Python: >=3.6
License-File: LICENSE
Requires-Dist: flask
Requires-Dist: dbhydra
